./.gitignore
./LICENSE
./PKG-INFO
./README.md
./pyproject.toml
./requirements.txt
./server.py
sealmetrics_mcp-0.3.0.dist-info/METADATA
sealmetrics_mcp-0.3.0.dist-info/WHEEL
sealmetrics_mcp-0.3.0.dist-info/entry_points.txt
sealmetrics_mcp-0.3.0.dist-info/licenses/LICENSE
sealmetrics_mcp-0.3.0.dist-info/RECORD
