Metadata-Version: 2.4
Name: sealmetrics-mcp
Version: 0.3.0
Summary: Model Context Protocol server for Sealmetrics analytics - query traffic, conversions, and marketing data with AI assistants
Project-URL: Homepage, https://sealmetrics.com
Project-URL: Documentation, https://github.com/sealmetrics/mcp-server#readme
Project-URL: Repository, https://github.com/sealmetrics/mcp-server
Project-URL: Issues, https://github.com/sealmetrics/mcp-server/issues
Author-email: Sealmetrics Team <support@sealmetrics.com>
License: MIT
License-File: LICENSE
Keywords: ai,analytics,claude,marketing,mcp,sealmetrics
Classifier: Development Status :: 4 - Beta
Classifier: Intended Audience :: Developers
Classifier: License :: OSI Approved :: MIT License
Classifier: Programming Language :: Python :: 3
Classifier: Programming Language :: Python :: 3.10
Classifier: Programming Language :: Python :: 3.11
Classifier: Programming Language :: Python :: 3.12
Classifier: Topic :: Software Development :: Libraries :: Python Modules
Requires-Python: >=3.10
Requires-Dist: httpx>=0.27.0
Requires-Dist: mcp>=0.9.0
Provides-Extra: dev
Requires-Dist: pytest-asyncio>=0.23.0; extra == 'dev'
Requires-Dist: pytest>=8.0.0; extra == 'dev'
